anoens/__init__.py
anoens/crm.py
anoens/methods.py
simplestat/__init__.py
simplestat/content.py
anoens-0.8.dist-info/LICENSE
anoens-0.8.dist-info/METADATA
anoens-0.8.dist-info/WHEEL
anoens-0.8.dist-info/top_level.txt
anoens-0.8.dist-info/RECORD
