Metadata-Version: 2.1
Name: anoens
Version: 0.8
Summary: Companion Module to my Paper "Evaluating and Comparing Heterogeneous Ensemble Methods for Unsupervised Anomaly Detection" (2023, IJCNN). Provides method to combine the scores of multiple anomaly detectors into an ensemble.
Home-page: https://github.com/psorus/anoens/
Download-URL: https://github.com/psorus/anoens/archive/0.8.tar.gz
Author: Simon Klüttermann
Author-email: Simon.Kluettermann@gmx.de
License: UNKNOWN
Platform: UNKNOWN
Classifier: Programming Language :: Python :: 3
Classifier: License :: OSI Approved :: MIT License
Classifier: Operating System :: OS Independent
Requires-Python: >=2.7
License-File: LICENSE
Requires-Dist: numpy
Requires-Dist: scipy
Requires-Dist: sklearn
